redpay/__init__.py
redpay/charge_ach.py
redpay/charge_card.py
redpay/charge_token.py
redpay/get_transaction.py
redpay/redpay.py
redpay/refund.py
redpay/session.py
redpay/tokenize_ach.py
redpay/tokenize_card.py
redpay/void.py
redpay-1.4.0.dist-info/LICENSE
redpay-1.4.0.dist-info/METADATA
redpay-1.4.0.dist-info/WHEEL
redpay-1.4.0.dist-info/top_level.txt
redpay-1.4.0.dist-info/RECORD
