Metadata-Version: 2.1
Name: redpay
Version: 1.4.0
Summary: Python API for integrating with the RedPay Engine
Home-page: https://bitbucket.org/redshepherdinc/python-api.git
Author: Red Shepherd Inc.
Author-email: support@redshepherd.com
License: UNKNOWN
Platform: UNKNOWN
Classifier: Development Status :: 5 - Production/Stable
Classifier: Intended Audience :: Developers
Classifier: Topic :: Software Development :: Build Tools
Classifier: License :: OSI Approved :: MIT License
Classifier: Programming Language :: Python :: 3
Classifier: Programming Language :: Python :: 3.4
Classifier: Programming Language :: Python :: 3.5
Classifier: Programming Language :: Python :: 3.6
Requires-Python: >=3.5
Requires-Dist: pycryptodome (>=3.9.9)
